README.md
setup.py
rann/RANN.py
rann/__init__.py
rann.egg-info/PKG-INFO
rann.egg-info/SOURCES.txt
rann.egg-info/dependency_links.txt
rann.egg-info/top_level.txt