Metadata-Version: 2.1
Name: rann
Version: 1.0.1
Summary: Random Neural Network
Home-page: https://github.com/bilkosem/random_neural_network
Author: bilkosem
Author-email: bilkos92@gmail.com
License: UNKNOWN
Platform: UNKNOWN
Classifier: Programming Language :: Python :: 3
Classifier: License :: OSI Approved :: MIT License
Classifier: Operating System :: OS Independent
